LICENSE
MANIFEST.in
README.md
requirements.extras.txt
requirements.txt
setup.py
eerily/__init__.py
eerily/version.py
eerily.egg-info/PKG-INFO
eerily.egg-info/SOURCES.txt
eerily.egg-info/dependency_links.txt
eerily.egg-info/not-zip-safe
eerily.egg-info/requires.txt
eerily.egg-info/top_level.txt
eerily/datasets/__init__.py
eerily/datasets/generators.py
eerily/generators/__init__.py
eerily/generators/brownian.py
eerily/generators/elasticity.py
eerily/generators/naive.py
eerily/generators/spiking.py
eerily/generators/var.py
eerily/generators/utils/__init__.py
eerily/generators/utils/base.py
eerily/generators/utils/choices.py
eerily/generators/utils/events.py
eerily/generators/utils/factory.py
eerily/generators/utils/noises.py
eerily/generators/utils/stepper.py
eerily/physics/__init__.py
eerily/physics/pendulum.py
tests/test_generators/__init__.py
tests/test_generators/conftest.py
tests/test_generators/test_brownian.py
tests/test_generators/test_elasticity.py
tests/test_generators/test_events.py
tests/test_generators/test_naive.py
tests/test_generators/test_noises.py
tests/test_generators/test_spiking.py
tests/test_generators/test_var.py
tests/test_generators/test_utils/__init__.py
tests/test_generators/test_utils/test_base.py
tests/test_generators/test_utils/test_choices.py
tests/test_generators/test_utils/test_stepper.py
tests/test_physics/__init__.py
tests/test_physics/test_pendulum.py