Metadata-Version: 2.1
Name: eerily
Version: 0.2.1
Summary: Time seRies plAYground (eerily) is a playground for time series
Home-page: https://github.com/emptymalei/eerily
Author: L Ma
Author-email: hi@leima.is
License: MIT
Provides-Extra: isort
Provides-Extra: tests
Provides-Extra: matplotlib
Provides-Extra: docs
Provides-Extra: mkdocs-autorefs
Provides-Extra: mkdocs-jupyter
Provides-Extra: mkdocs-material
Provides-Extra: mkdocstrings-python
Provides-Extra: mkdocstrings[python]
Provides-Extra: pytest
Provides-Extra: pytest-cov
Provides-Extra: all
License-File: LICENSE
